cbz/__init__.py
cbz/__main__.py
cbz/cbz.ico
cbz/comic.py
cbz/constants.py
cbz/models.py
cbz/page.py
cbz/player.py
cbz/utils.py
cbz-3.4.5.dist-info/entry_points.txt
cbz-3.4.5.dist-info/LICENSE
cbz-3.4.5.dist-info/METADATA
cbz-3.4.5.dist-info/WHEEL
cbz-3.4.5.dist-info/RECORD
