Metadata-Version: 2.1
Name: cbz
Version: 3.4.5
Summary: CBZ simplifies creating, managing, and viewing comic book files in CBZ, CBR, and PDF formats, offering seamless packaging, metadata handling and built-in viewing capabilities.
Home-page: https://github.com/hyugogirubato/cbz
License: MIT
Keywords: python,cbz,cbr,pdf,ebooks,manga,comics,webtoons
Author: hyugogirubato
Author-email: 65763543+hyugogirubato@users.noreply.github.com
Requires-Python: >=3.8,<4.0
Classifier: Development Status :: 5 - Production/Stable
Classifier: Intended Audience :: Developers
Classifier: Intended Audience :: End Users/Desktop
Classifier: License :: OSI Approved :: MIT License
Classifier: Natural Language :: English
Classifier: Operating System :: OS Independent
Classifier: Programming Language :: Python :: 3
Classifier: Programming Language :: Python :: 3.8
Classifier: Programming Language :: Python :: 3.9
Classifier: Programming Language :: Python :: 3.10
Classifier: Programming Language :: Python :: 3.11
Classifier: Programming Language :: Python :: 3.12
Classifier: Topic :: Software Development :: Libraries :: Python Modules
Classifier: Topic :: Utilities
Provides-Extra: pillow
Requires-Dist: Pillow (>=10.4.0)
Requires-Dist: langcodes (>=3.4.0)
Requires-Dist: pillow-avif-plugin (>=1.5.2) ; (python_version >= "3.9") and (extra == "pillow")
Requires-Dist: pillow-jxl-plugin (>=1.3.4) ; (python_version >= "3.9") and (extra == "pillow")
Requires-Dist: pypdf (>=5.7.0)
Requires-Dist: rarfile (>=4.2)
Requires-Dist: xmltodict (>=0.14.2)
Project-URL: Changelog, https://github.com/hyugogirubato/cbz/blob/main/CHANGELOG.md
Project-URL: Issues, https://github.com/hyugogirubato/cbz/issues
Project-URL: Repository, https://github.com/hyugogirubato/cbz
